{"adult":false,"also_known_as":["Кэтрин Уотерстон","캐서린 워터스턴","كاثرين واترستون","キャサリン・ウォーターストン","凱薩琳·華特斯頓"],"biography":"Katherine Boyer Waterston (born March 3, 1980) is an American actress. She made her feature film debut in Michael Clayton (2007). She then had supporting roles in films including Robot & Frank, Being Flynn (both 2012) and The Disappearance of Eleanor Rigby: Her (2013) before her leading role as Shasta Fay Hepworth in Paul Thomas Anderson's Inherent Vice (2014). In 2015, she portrayed Chrisann Brennan in Steve Jobs. She had starring roles in the Harry Potter prequel, Fantastic Beasts and Where to Find Them (2016), and Alien: Covenant (2017), a prequel to Ridley Scott's Alien film series.","birthday":"1980-03-03","id":77795,"imdb_id":"nm2239702","name":"Katherine Waterston","place_of_birth":"Westminster, London, England, UK","popularity":5.233,"profile_path":"/zgLVX4KJJ6hTD2niGLchkzjfWpJ.jpg","images":{"profiles":[{"file_path":"/hSVc393Xi491nAn18MVju6Myj2p.jpg","width":615,"height":922,"aspect_ratio":0.66702819956616},{"file_path":"/zgLVX4KJJ6hTD2niGLchkzjfWpJ.jpg","width":493,"height":740,"aspect_ratio":0.66621621621622},{"file_path":"/t18erLI4iITwAZmjSeGSzLN0WMS.jpg","width":762,"height":1143,"aspect_ratio":0.66666666666667},{"file_path":"/x7WN8B1DB9RCptRZdzCN7fBjA61.jpg","width":663,"height":995,"aspect_ratio":0.66633165829146},{"file_path":"/fKKdWB0zupokMSgYIb1VNjnaTvl.jpg","width":600,"height":900,"aspect_ratio":0.66666666666667},{"file_path":"/xkPBBGQt2jkYwuMiENBFjrr6pY5.jpg","width":600,"height":900,"aspect_ratio":0.66666666666667},{"file_path":"/sTRMVlpasY3EbceLNrMiYWdtqcP.jpg","width":749,"height":1123,"aspect_ratio":0.66696349065004},{"file_path":"/5fIEhBldLuIkFK0R3USTzngyE3c.jpg","width":683,"height":1024,"aspect_ratio":0.6669921875}]},"external_ids":{"imdb_id":"nm2239702","tvrage_id":0}}